headline_detector/__init__.py
headline_detector/detector.py
headline_detector/hyper_params.py
headline_detector/model.py
headline_detector/model_checkpoint.py
headline_detector/preprocessing_scenario.py
headline_detector/utils.py
headline_detector/processing_pipeline/__init__.py
headline_detector/processing_pipeline/pipeline.py
headline_detector/processing_pipeline/processing_func.py
headline_detector/processing_pipeline/stemmer.py
headline_detector-1.0.3.dist-info/LICENSE
headline_detector-1.0.3.dist-info/METADATA
headline_detector-1.0.3.dist-info/WHEEL
headline_detector-1.0.3.dist-info/top_level.txt
headline_detector-1.0.3.dist-info/RECORD
